pmpca/__init__.py
pmpca/pmpca.py
pmpca-0.1.2.dist-info/LICENSE
pmpca-0.1.2.dist-info/METADATA
pmpca-0.1.2.dist-info/WHEEL
pmpca-0.1.2.dist-info/top_level.txt
pmpca-0.1.2.dist-info/RECORD
