Metadata-Version: 2.1
Name: pmpca
Version: 0.1.2
Summary: PCA for multivariate statistical process monitoring.
Home-page: https://github.com/afraniomelo/pmpca
Author: Afrânio Melo
Author-email: afraeq@gmail.com
License: MIT
Platform: UNKNOWN
Requires-Python: >=3.7
Requires-Dist: numpy (>=1.21.6)
Requires-Dist: pandas (>=1.3.5)
Requires-Dist: matplotlib (>=3.5.2)
